pysudo/__init__.py
pysudo/main.py
pysudo-1.1.0.dist-info/LICENSE.txt
pysudo-1.1.0.dist-info/METADATA
pysudo-1.1.0.dist-info/WHEEL
pysudo-1.1.0.dist-info/top_level.txt
pysudo-1.1.0.dist-info/RECORD
