Metadata-Version: 2.1
Name: pysudo
Version: 1.1.0
Summary: libray for solving standard Sudoku
Home-page: https://github.com/YashIndane/pysudo
Author: Yash Indane
Author-email: yashindane46@gmail.com
License: UNKNOWN
Platform: UNKNOWN
Classifier: Programming Language :: Python :: 3
Classifier: License :: OSI Approved :: MIT License
Classifier: Operating System :: OS Independent
Requires-Python: >=3.6
License-File: LICENSE.txt
